{
  "meta": {
    "title": "Employment costs & net pay (Skuad live calculator)",
    "source": "Skuad cost-calculator API (engine behind boundlesshq.com/cost-calculator)",
    "endpoint": "https://cost-calculator.skuad.io/cost-calculator/cost",
    "currency": "EUR",
    "fetched": "2026-06-25",
    "salaryPoints": [
      20000,
      30000,
      40000,
      50000,
      60000,
      70000,
      80000,
      90000,
      100000,
      110000,
      120000,
      130000,
      140000,
      150000
    ],
    "note": "European countries fetched live from the Skuad API at several gross-salary points (genuine per-country calculation; may differ from the eBook study). Slovenia is unavailable in the API. US cities reuse the blog figures because the API's US state income tax is unreliable. Cost of living reuses the eBook. Figures are estimates for comparison only."
  },
  "countries": [
    {
      "name": "Albania",
      "flag": "🇦🇱",
      "eu": false,
      "devSalary": 26300,
      "costOfLiving": 14101,
      "points": [
        {
          "gross": 20000,
          "cost": 27653,
          "net": 12880
        },
        {
          "gross": 30000,
          "cost": 38710,
          "net": 20544
        },
        {
          "gross": 40000,
          "cost": 49743,
          "net": 28244
        },
        {
          "gross": 50000,
          "cost": 60776,
          "net": 35944
        },
        {
          "gross": 60000,
          "cost": 71809,
          "net": 43644
        },
        {
          "gross": 70000,
          "cost": 82842,
          "net": 51344
        },
        {
          "gross": 80000,
          "cost": 93875,
          "net": 59044
        },
        {
          "gross": 90000,
          "cost": 104908,
          "net": 66744
        },
        {
          "gross": 100000,
          "cost": 115941,
          "net": 74444
        },
        {
          "gross": 110000,
          "cost": 126974,
          "net": 82144
        },
        {
          "gross": 120000,
          "cost": 138007,
          "net": 89844
        },
        {
          "gross": 130000,
          "cost": 149040,
          "net": 97544
        },
        {
          "gross": 140000,
          "cost": 160073,
          "net": 105244
        },
        {
          "gross": 150000,
          "cost": 171106,
          "net": 112944
        }
      ]
    },
    {
      "name": "Austria",
      "flag": "🇦🇹",
      "eu": true,
      "devSalary": 61000,
      "costOfLiving": 23387,
      "points": [
        {
          "gross": 20000,
          "cost": 36091,
          "net": 15038
        },
        {
          "gross": 30000,
          "cost": 51445,
          "net": 20387
        },
        {
          "gross": 40000,
          "cost": 66799,
          "net": 25159
        },
        {
          "gross": 50000,
          "cost": 82153,
          "net": 29347
        },
        {
          "gross": 60000,
          "cost": 97507,
          "net": 33535
        },
        {
          "gross": 70000,
          "cost": 112860,
          "net": 37656
        },
        {
          "gross": 80000,
          "cost": 128214,
          "net": 41044
        },
        {
          "gross": 90000,
          "cost": 143568,
          "net": 44432
        },
        {
          "gross": 100000,
          "cost": 158922,
          "net": 47820
        },
        {
          "gross": 110000,
          "cost": 174276,
          "net": 51070
        },
        {
          "gross": 120000,
          "cost": 189629,
          "net": 54258
        },
        {
          "gross": 130000,
          "cost": 204983,
          "net": 57446
        },
        {
          "gross": 140000,
          "cost": 220337,
          "net": 60634
        },
        {
          "gross": 150000,
          "cost": 235691,
          "net": 63822
        }
      ]
    },
    {
      "name": "Belgium",
      "flag": "🇧🇪",
      "eu": true,
      "devSalary": 55700,
      "costOfLiving": 21526,
      "points": [
        {
          "gross": 20000,
          "cost": 30844,
          "net": 12151
        },
        {
          "gross": 30000,
          "cost": 43844,
          "net": 16888
        },
        {
          "gross": 40000,
          "cost": 56844,
          "net": 21265
        },
        {
          "gross": 50000,
          "cost": 69844,
          "net": 25643
        },
        {
          "gross": 60000,
          "cost": 82844,
          "net": 29605
        },
        {
          "gross": 70000,
          "cost": 95844,
          "net": 33645
        },
        {
          "gross": 80000,
          "cost": 108844,
          "net": 37687
        },
        {
          "gross": 90000,
          "cost": 121844,
          "net": 41729
        },
        {
          "gross": 100000,
          "cost": 134844,
          "net": 45772
        },
        {
          "gross": 110000,
          "cost": 147844,
          "net": 49814
        },
        {
          "gross": 120000,
          "cost": 160844,
          "net": 53856
        },
        {
          "gross": 130000,
          "cost": 173844,
          "net": 57898
        },
        {
          "gross": 140000,
          "cost": 186844,
          "net": 61941
        },
        {
          "gross": 150000,
          "cost": 199844,
          "net": 65983
        }
      ]
    },
    {
      "name": "Bulgaria",
      "flag": "🇧🇬",
      "eu": true,
      "devSalary": 27700,
      "costOfLiving": 12307,
      "points": [
        {
          "gross": 20000,
          "cost": 27430,
          "net": 15463
        },
        {
          "gross": 30000,
          "cost": 38646,
          "net": 24463
        },
        {
          "gross": 40000,
          "cost": 48846,
          "net": 33463
        },
        {
          "gross": 50000,
          "cost": 59046,
          "net": 42463
        },
        {
          "gross": 60000,
          "cost": 69246,
          "net": 51463
        },
        {
          "gross": 70000,
          "cost": 79446,
          "net": 60463
        },
        {
          "gross": 80000,
          "cost": 89646,
          "net": 69463
        },
        {
          "gross": 90000,
          "cost": 99846,
          "net": 78463
        },
        {
          "gross": 100000,
          "cost": 110046,
          "net": 87463
        },
        {
          "gross": 110000,
          "cost": 120246,
          "net": 96463
        },
        {
          "gross": 120000,
          "cost": 130446,
          "net": 105463
        },
        {
          "gross": 130000,
          "cost": 140646,
          "net": 114463
        },
        {
          "gross": 140000,
          "cost": 150846,
          "net": 123463
        },
        {
          "gross": 150000,
          "cost": 161046,
          "net": 132463
        }
      ]
    },
    {
      "name": "Croatia",
      "flag": "🇭🇷",
      "eu": true,
      "devSalary": 45300,
      "costOfLiving": 16840,
      "points": [
        {
          "gross": 20000,
          "cost": 27465,
          "net": 11280
        },
        {
          "gross": 30000,
          "cost": 39315,
          "net": 16920
        },
        {
          "gross": 40000,
          "cost": 51165,
          "net": 22560
        },
        {
          "gross": 50000,
          "cost": 63015,
          "net": 28200
        },
        {
          "gross": 60000,
          "cost": 74865,
          "net": 33840
        },
        {
          "gross": 70000,
          "cost": 86715,
          "net": 38300
        },
        {
          "gross": 80000,
          "cost": 98565,
          "net": 42760
        },
        {
          "gross": 90000,
          "cost": 110415,
          "net": 47220
        },
        {
          "gross": 100000,
          "cost": 122265,
          "net": 51680
        },
        {
          "gross": 110000,
          "cost": 134115,
          "net": 56140
        },
        {
          "gross": 120000,
          "cost": 145965,
          "net": 62136
        },
        {
          "gross": 130000,
          "cost": 157815,
          "net": 68596
        },
        {
          "gross": 140000,
          "cost": 169665,
          "net": 75056
        },
        {
          "gross": 150000,
          "cost": 181515,
          "net": 81516
        }
      ]
    },
    {
      "name": "Cyprus",
      "flag": "🇨🇾",
      "eu": true,
      "devSalary": 48200,
      "costOfLiving": 21853,
      "points": [
        {
          "gross": 20000,
          "cost": 27785,
          "net": 17610
        },
        {
          "gross": 30000,
          "cost": 39525,
          "net": 24365
        },
        {
          "gross": 40000,
          "cost": 51265,
          "net": 30535
        },
        {
          "gross": 50000,
          "cost": 63005,
          "net": 36390
        },
        {
          "gross": 60000,
          "cost": 74745,
          "net": 42245
        },
        {
          "gross": 70000,
          "cost": 86370,
          "net": 47696
        },
        {
          "gross": 80000,
          "cost": 97060,
          "net": 53931
        },
        {
          "gross": 90000,
          "cost": 107750,
          "net": 60166
        },
        {
          "gross": 100000,
          "cost": 118440,
          "net": 66401
        },
        {
          "gross": 110000,
          "cost": 129130,
          "net": 72636
        },
        {
          "gross": 120000,
          "cost": 139820,
          "net": 78871
        },
        {
          "gross": 130000,
          "cost": 150510,
          "net": 85106
        },
        {
          "gross": 140000,
          "cost": 161200,
          "net": 91341
        },
        {
          "gross": 150000,
          "cost": 171890,
          "net": 97576
        }
      ]
    },
    {
      "name": "Czech Republic",
      "flag": "🇨🇿",
      "eu": true,
      "devSalary": 37700,
      "costOfLiving": 17769,
      "points": [
        {
          "gross": 20000,
          "cost": 30498,
          "net": 14680
        },
        {
          "gross": 30000,
          "cost": 44134,
          "net": 22020
        },
        {
          "gross": 40000,
          "cost": 57770,
          "net": 29360
        },
        {
          "gross": 50000,
          "cost": 71406,
          "net": 36700
        },
        {
          "gross": 60000,
          "cost": 85042,
          "net": 44040
        },
        {
          "gross": 70000,
          "cost": 98678,
          "net": 51380
        },
        {
          "gross": 80000,
          "cost": 112314,
          "net": 58023
        },
        {
          "gross": 90000,
          "cost": 125950,
          "net": 64563
        },
        {
          "gross": 100000,
          "cost": 138360,
          "net": 71787
        },
        {
          "gross": 110000,
          "cost": 149516,
          "net": 79037
        },
        {
          "gross": 120000,
          "cost": 160672,
          "net": 86287
        },
        {
          "gross": 130000,
          "cost": 171828,
          "net": 93537
        },
        {
          "gross": 140000,
          "cost": 182984,
          "net": 100787
        },
        {
          "gross": 150000,
          "cost": 194140,
          "net": 108037
        }
      ]
    },
    {
      "name": "Denmark",
      "flag": "🇩🇰",
      "eu": true,
      "devSalary": 65500,
      "costOfLiving": 25803,
      "points": [
        {
          "gross": 20000,
          "cost": 29473,
          "net": 12205
        },
        {
          "gross": 30000,
          "cost": 41023,
          "net": 17405
        },
        {
          "gross": 40000,
          "cost": 52573,
          "net": 22605
        },
        {
          "gross": 50000,
          "cost": 64123,
          "net": 27805
        },
        {
          "gross": 60000,
          "cost": 75673,
          "net": 33005
        },
        {
          "gross": 70000,
          "cost": 87223,
          "net": 38205
        },
        {
          "gross": 80000,
          "cost": 98773,
          "net": 41998
        },
        {
          "gross": 90000,
          "cost": 110323,
          "net": 45548
        },
        {
          "gross": 100000,
          "cost": 121873,
          "net": 49098
        },
        {
          "gross": 110000,
          "cost": 133423,
          "net": 52648
        },
        {
          "gross": 120000,
          "cost": 144973,
          "net": 56198
        },
        {
          "gross": 130000,
          "cost": 156523,
          "net": 59748
        },
        {
          "gross": 140000,
          "cost": 168073,
          "net": 63298
        },
        {
          "gross": 150000,
          "cost": 179623,
          "net": 66848
        }
      ]
    },
    {
      "name": "Estonia",
      "flag": "🇪🇪",
      "eu": true,
      "devSalary": 31900,
      "costOfLiving": 18114,
      "points": [
        {
          "gross": 20000,
          "cost": 33062,
          "net": 14880
        },
        {
          "gross": 30000,
          "cost": 47980,
          "net": 22320
        },
        {
          "gross": 40000,
          "cost": 62898,
          "net": 29760
        },
        {
          "gross": 50000,
          "cost": 77816,
          "net": 37200
        },
        {
          "gross": 60000,
          "cost": 92734,
          "net": 44640
        },
        {
          "gross": 70000,
          "cost": 107652,
          "net": 52080
        },
        {
          "gross": 80000,
          "cost": 122570,
          "net": 59520
        },
        {
          "gross": 90000,
          "cost": 137488,
          "net": 66960
        },
        {
          "gross": 100000,
          "cost": 152406,
          "net": 74400
        },
        {
          "gross": 110000,
          "cost": 167324,
          "net": 81840
        },
        {
          "gross": 120000,
          "cost": 182242,
          "net": 89280
        },
        {
          "gross": 130000,
          "cost": 197160,
          "net": 96720
        },
        {
          "gross": 140000,
          "cost": 212078,
          "net": 104160
        },
        {
          "gross": 150000,
          "cost": 226996,
          "net": 111600
        }
      ]
    },
    {
      "name": "Finland",
      "flag": "🇫🇮",
      "eu": true,
      "devSalary": 59000,
      "costOfLiving": 20472,
      "points": [
        {
          "gross": 20000,
          "cost": 28233,
          "net": 14372
        },
        {
          "gross": 30000,
          "cost": 40467,
          "net": 20592
        },
        {
          "gross": 40000,
          "cost": 52701,
          "net": 25923
        },
        {
          "gross": 50000,
          "cost": 64935,
          "net": 31090
        },
        {
          "gross": 60000,
          "cost": 77169,
          "net": 36021
        },
        {
          "gross": 70000,
          "cost": 89403,
          "net": 40952
        },
        {
          "gross": 80000,
          "cost": 101637,
          "net": 45883
        },
        {
          "gross": 90000,
          "cost": 113871,
          "net": 49864
        },
        {
          "gross": 100000,
          "cost": 126105,
          "net": 53795
        },
        {
          "gross": 110000,
          "cost": 138339,
          "net": 57726
        },
        {
          "gross": 120000,
          "cost": 150573,
          "net": 61657
        },
        {
          "gross": 130000,
          "cost": 162807,
          "net": 65588
        },
        {
          "gross": 140000,
          "cost": 175041,
          "net": 69519
        },
        {
          "gross": 150000,
          "cost": 187275,
          "net": 73450
        }
      ]
    },
    {
      "name": "France",
      "flag": "🇫🇷",
      "eu": true,
      "devSalary": 50400,
      "costOfLiving": 20626,
      "points": [
        {
          "gross": 20000,
          "cost": 34759,
          "net": 16969
        },
        {
          "gross": 30000,
          "cost": 49986,
          "net": 24084
        },
        {
          "gross": 40000,
          "cost": 65213,
          "net": 30114
        },
        {
          "gross": 50000,
          "cost": 80401,
          "net": 36144
        },
        {
          "gross": 60000,
          "cost": 95428,
          "net": 42174
        },
        {
          "gross": 70000,
          "cost": 110455,
          "net": 48204
        },
        {
          "gross": 80000,
          "cost": 125482,
          "net": 53521
        },
        {
          "gross": 90000,
          "cost": 140509,
          "net": 58451
        },
        {
          "gross": 100000,
          "cost": 155536,
          "net": 63381
        },
        {
          "gross": 110000,
          "cost": 170563,
          "net": 68311
        },
        {
          "gross": 120000,
          "cost": 185590,
          "net": 73241
        },
        {
          "gross": 130000,
          "cost": 200617,
          "net": 78171
        },
        {
          "gross": 140000,
          "cost": 215644,
          "net": 83101
        },
        {
          "gross": 150000,
          "cost": 230671,
          "net": 88031
        }
      ]
    },
    {
      "name": "Germany",
      "flag": "🇩🇪",
      "eu": true,
      "devSalary": 65200,
      "costOfLiving": 22558,
      "points": [
        {
          "gross": 20000,
          "cost": 30282,
          "net": 13552
        },
        {
          "gross": 30000,
          "cost": 42941,
          "net": 19670
        },
        {
          "gross": 40000,
          "cost": 55600,
          "net": 25787
        },
        {
          "gross": 50000,
          "cost": 68259,
          "net": 31905
        },
        {
          "gross": 60000,
          "cost": 80918,
          "net": 37196
        },
        {
          "gross": 70000,
          "cost": 93551,
          "net": 40336
        },
        {
          "gross": 80000,
          "cost": 105155,
          "net": 44286
        },
        {
          "gross": 90000,
          "cost": 116759,
          "net": 48236
        },
        {
          "gross": 100000,
          "cost": 128363,
          "net": 52186
        },
        {
          "gross": 110000,
          "cost": 138760,
          "net": 57039
        },
        {
          "gross": 120000,
          "cost": 148960,
          "net": 62039
        },
        {
          "gross": 130000,
          "cost": 159160,
          "net": 67039
        },
        {
          "gross": 140000,
          "cost": 169360,
          "net": 72039
        },
        {
          "gross": 150000,
          "cost": 179560,
          "net": 77039
        }
      ]
    },
    {
      "name": "Greece",
      "flag": "🇬🇷",
      "eu": true,
      "devSalary": 39200,
      "costOfLiving": 15288,
      "points": [
        {
          "gross": 20000,
          "cost": 28084,
          "net": 14126
        },
        {
          "gross": 30000,
          "cost": 40513,
          "net": 19939
        },
        {
          "gross": 40000,
          "cost": 52942,
          "net": 24952
        },
        {
          "gross": 50000,
          "cost": 65371,
          "net": 29165
        },
        {
          "gross": 60000,
          "cost": 77800,
          "net": 33378
        },
        {
          "gross": 70000,
          "cost": 90229,
          "net": 37591
        },
        {
          "gross": 80000,
          "cost": 102658,
          "net": 41804
        },
        {
          "gross": 90000,
          "cost": 115087,
          "net": 46638
        },
        {
          "gross": 100000,
          "cost": 125481,
          "net": 52238
        },
        {
          "gross": 110000,
          "cost": 135681,
          "net": 57838
        },
        {
          "gross": 120000,
          "cost": 145881,
          "net": 63438
        },
        {
          "gross": 130000,
          "cost": 156081,
          "net": 69038
        },
        {
          "gross": 140000,
          "cost": 166281,
          "net": 74638
        },
        {
          "gross": 150000,
          "cost": 176481,
          "net": 80238
        }
      ]
    },
    {
      "name": "Hungary",
      "flag": "🇭🇺",
      "eu": true,
      "devSalary": 42200,
      "costOfLiving": 13530,
      "points": [
        {
          "gross": 20000,
          "cost": 26226,
          "net": 13300
        },
        {
          "gross": 30000,
          "cost": 37726,
          "net": 19950
        },
        {
          "gross": 40000,
          "cost": 49226,
          "net": 26600
        },
        {
          "gross": 50000,
          "cost": 60726,
          "net": 33250
        },
        {
          "gross": 60000,
          "cost": 72226,
          "net": 39900
        },
        {
          "gross": 70000,
          "cost": 83726,
          "net": 46550
        },
        {
          "gross": 80000,
          "cost": 95226,
          "net": 53200
        },
        {
          "gross": 90000,
          "cost": 106726,
          "net": 59850
        },
        {
          "gross": 100000,
          "cost": 118226,
          "net": 66500
        },
        {
          "gross": 110000,
          "cost": 129726,
          "net": 73150
        },
        {
          "gross": 120000,
          "cost": 141226,
          "net": 79800
        },
        {
          "gross": 130000,
          "cost": 152726,
          "net": 86450
        },
        {
          "gross": 140000,
          "cost": 164226,
          "net": 93100
        },
        {
          "gross": 150000,
          "cost": 175726,
          "net": 99750
        }
      ]
    },
    {
      "name": "Ireland",
      "flag": "🇮🇪",
      "eu": true,
      "devSalary": 66500,
      "costOfLiving": 31533,
      "points": [
        {
          "gross": 20000,
          "cost": 27794,
          "net": 14640
        },
        {
          "gross": 30000,
          "cost": 39269,
          "net": 21857
        },
        {
          "gross": 40000,
          "cost": 50744,
          "net": 28987
        },
        {
          "gross": 50000,
          "cost": 62219,
          "net": 34917
        },
        {
          "gross": 60000,
          "cost": 73694,
          "net": 40047
        },
        {
          "gross": 70000,
          "cost": 85169,
          "net": 45177
        },
        {
          "gross": 80000,
          "cost": 96644,
          "net": 49809
        },
        {
          "gross": 90000,
          "cost": 108119,
          "net": 54439
        },
        {
          "gross": 100000,
          "cost": 119594,
          "net": 59069
        },
        {
          "gross": 110000,
          "cost": 131069,
          "net": 63699
        },
        {
          "gross": 120000,
          "cost": 142544,
          "net": 68329
        },
        {
          "gross": 130000,
          "cost": 154019,
          "net": 72959
        },
        {
          "gross": 140000,
          "cost": 165494,
          "net": 77589
        },
        {
          "gross": 150000,
          "cost": 176969,
          "net": 82219
        }
      ]
    },
    {
      "name": "Italy",
      "flag": "🇮🇹",
      "eu": true,
      "devSalary": 44200,
      "costOfLiving": 19513,
      "points": [
        {
          "gross": 20000,
          "cost": 38515,
          "net": 13114
        },
        {
          "gross": 30000,
          "cost": 53102,
          "net": 19471
        },
        {
          "gross": 40000,
          "cost": 67689,
          "net": 25028
        },
        {
          "gross": 50000,
          "cost": 82276,
          "net": 30585
        },
        {
          "gross": 60000,
          "cost": 96863,
          "net": 35142
        },
        {
          "gross": 70000,
          "cost": 111450,
          "net": 39699
        },
        {
          "gross": 80000,
          "cost": 126037,
          "net": 44256
        },
        {
          "gross": 90000,
          "cost": 140624,
          "net": 48813
        },
        {
          "gross": 100000,
          "cost": 155211,
          "net": 53370
        },
        {
          "gross": 110000,
          "cost": 169798,
          "net": 57927
        },
        {
          "gross": 120000,
          "cost": 184385,
          "net": 62484
        },
        {
          "gross": 130000,
          "cost": 198972,
          "net": 67041
        },
        {
          "gross": 140000,
          "cost": 213559,
          "net": 71598
        },
        {
          "gross": 150000,
          "cost": 228146,
          "net": 76155
        }
      ]
    },
    {
      "name": "Latvia",
      "flag": "🇱🇻",
      "eu": true,
      "devSalary": 35900,
      "costOfLiving": 14635,
      "points": [
        {
          "gross": 20000,
          "cost": 30502,
          "net": 13900
        },
        {
          "gross": 30000,
          "cost": 43061,
          "net": 20550
        },
        {
          "gross": 40000,
          "cost": 55620,
          "net": 27200
        },
        {
          "gross": 50000,
          "cost": 68179,
          "net": 33850
        },
        {
          "gross": 60000,
          "cost": 80738,
          "net": 40500
        },
        {
          "gross": 70000,
          "cost": 93297,
          "net": 46502
        },
        {
          "gross": 80000,
          "cost": 105856,
          "net": 52252
        },
        {
          "gross": 90000,
          "cost": 118415,
          "net": 58002
        },
        {
          "gross": 100000,
          "cost": 130974,
          "net": 63752
        },
        {
          "gross": 110000,
          "cost": 143533,
          "net": 69502
        },
        {
          "gross": 120000,
          "cost": 156092,
          "net": 75252
        },
        {
          "gross": 130000,
          "cost": 168651,
          "net": 81002
        },
        {
          "gross": 140000,
          "cost": 181210,
          "net": 86752
        },
        {
          "gross": 150000,
          "cost": 193769,
          "net": 92502
        }
      ]
    },
    {
      "name": "Lithuania",
      "flag": "🇱🇹",
      "eu": true,
      "devSalary": 41900,
      "costOfLiving": 16603,
      "points": [
        {
          "gross": 20000,
          "cost": 24665,
          "net": 12100
        },
        {
          "gross": 30000,
          "cost": 35115,
          "net": 18150
        },
        {
          "gross": 40000,
          "cost": 45565,
          "net": 24200
        },
        {
          "gross": 50000,
          "cost": 56015,
          "net": 30250
        },
        {
          "gross": 60000,
          "cost": 66465,
          "net": 36300
        },
        {
          "gross": 70000,
          "cost": 76915,
          "net": 42350
        },
        {
          "gross": 80000,
          "cost": 87365,
          "net": 48400
        },
        {
          "gross": 90000,
          "cost": 97815,
          "net": 54098
        },
        {
          "gross": 100000,
          "cost": 108265,
          "net": 59648
        },
        {
          "gross": 110000,
          "cost": 118715,
          "net": 65198
        },
        {
          "gross": 120000,
          "cost": 129165,
          "net": 70748
        },
        {
          "gross": 130000,
          "cost": 139615,
          "net": 76298
        },
        {
          "gross": 140000,
          "cost": 150065,
          "net": 81727
        },
        {
          "gross": 150000,
          "cost": 160515,
          "net": 86577
        }
      ]
    },
    {
      "name": "Luxembourg",
      "flag": "🇱🇺",
      "eu": true,
      "devSalary": 74900,
      "costOfLiving": 33295,
      "points": [
        {
          "gross": 20000,
          "cost": 29896,
          "net": 17410
        },
        {
          "gross": 30000,
          "cost": 41343,
          "net": 26115
        },
        {
          "gross": 40000,
          "cost": 52790,
          "net": 34820
        },
        {
          "gross": 50000,
          "cost": 64237,
          "net": 43525
        },
        {
          "gross": 60000,
          "cost": 75684,
          "net": 52230
        },
        {
          "gross": 70000,
          "cost": 87131,
          "net": 60935
        },
        {
          "gross": 80000,
          "cost": 98578,
          "net": 69640
        },
        {
          "gross": 90000,
          "cost": 110025,
          "net": 78345
        },
        {
          "gross": 100000,
          "cost": 121472,
          "net": 87050
        },
        {
          "gross": 110000,
          "cost": 132919,
          "net": 95755
        },
        {
          "gross": 120000,
          "cost": 144366,
          "net": 104460
        },
        {
          "gross": 130000,
          "cost": 155813,
          "net": 113165
        },
        {
          "gross": 140000,
          "cost": 167260,
          "net": 121870
        },
        {
          "gross": 150000,
          "cost": 178707,
          "net": 130575
        }
      ]
    },
    {
      "name": "Malta",
      "flag": "🇲🇹",
      "eu": true,
      "devSalary": 60900,
      "costOfLiving": 21054,
      "points": [
        {
          "gross": 20000,
          "cost": 28213,
          "net": 14907
        },
        {
          "gross": 30000,
          "cost": 38413,
          "net": 22407
        },
        {
          "gross": 40000,
          "cost": 48613,
          "net": 29907
        },
        {
          "gross": 50000,
          "cost": 58813,
          "net": 37407
        },
        {
          "gross": 60000,
          "cost": 69013,
          "net": 44907
        },
        {
          "gross": 70000,
          "cost": 79213,
          "net": 51407
        },
        {
          "gross": 80000,
          "cost": 89413,
          "net": 57907
        },
        {
          "gross": 90000,
          "cost": 99613,
          "net": 64407
        },
        {
          "gross": 100000,
          "cost": 109813,
          "net": 70907
        },
        {
          "gross": 110000,
          "cost": 120013,
          "net": 77407
        },
        {
          "gross": 120000,
          "cost": 130213,
          "net": 83907
        },
        {
          "gross": 130000,
          "cost": 140413,
          "net": 90407
        },
        {
          "gross": 140000,
          "cost": 150613,
          "net": 96907
        },
        {
          "gross": 150000,
          "cost": 160813,
          "net": 103407
        }
      ]
    },
    {
      "name": "Moldova",
      "flag": "🇲🇩",
      "eu": false,
      "devSalary": 26000,
      "costOfLiving": 13002,
      "points": [
        {
          "gross": 20000,
          "cost": 29253,
          "net": 15500
        },
        {
          "gross": 30000,
          "cost": 42536,
          "net": 23250
        },
        {
          "gross": 40000,
          "cost": 55819,
          "net": 31000
        },
        {
          "gross": 50000,
          "cost": 69102,
          "net": 38750
        },
        {
          "gross": 60000,
          "cost": 82385,
          "net": 46500
        },
        {
          "gross": 70000,
          "cost": 95668,
          "net": 54250
        },
        {
          "gross": 80000,
          "cost": 108951,
          "net": 62000
        },
        {
          "gross": 90000,
          "cost": 122234,
          "net": 69750
        },
        {
          "gross": 100000,
          "cost": 135517,
          "net": 77500
        },
        {
          "gross": 110000,
          "cost": 148800,
          "net": 85250
        },
        {
          "gross": 120000,
          "cost": 162083,
          "net": 93000
        },
        {
          "gross": 130000,
          "cost": 175366,
          "net": 100750
        },
        {
          "gross": 140000,
          "cost": 188649,
          "net": 108500
        },
        {
          "gross": 150000,
          "cost": 201932,
          "net": 116250
        }
      ]
    },
    {
      "name": "Montenegro",
      "flag": "🇲🇪",
      "eu": false,
      "devSalary": 28000,
      "costOfLiving": 14714,
      "points": [
        {
          "gross": 20000,
          "cost": 24741,
          "net": 16161
        },
        {
          "gross": 30000,
          "cost": 35283,
          "net": 23611
        },
        {
          "gross": 40000,
          "cost": 45825,
          "net": 31061
        },
        {
          "gross": 50000,
          "cost": 56367,
          "net": 38511
        },
        {
          "gross": 60000,
          "cost": 66909,
          "net": 45961
        },
        {
          "gross": 70000,
          "cost": 77451,
          "net": 53411
        },
        {
          "gross": 80000,
          "cost": 87993,
          "net": 60861
        },
        {
          "gross": 90000,
          "cost": 98535,
          "net": 68311
        },
        {
          "gross": 100000,
          "cost": 109077,
          "net": 75761
        },
        {
          "gross": 110000,
          "cost": 119619,
          "net": 83211
        },
        {
          "gross": 120000,
          "cost": 130161,
          "net": 90661
        },
        {
          "gross": 130000,
          "cost": 140703,
          "net": 98111
        },
        {
          "gross": 140000,
          "cost": 151245,
          "net": 105561
        },
        {
          "gross": 150000,
          "cost": 161787,
          "net": 113011
        }
      ]
    },
    {
      "name": "Netherlands",
      "flag": "🇳🇱",
      "eu": true,
      "devSalary": 62800,
      "costOfLiving": 28590,
      "points": [
        {
          "gross": 20000,
          "cost": 34247,
          "net": 12836
        },
        {
          "gross": 30000,
          "cost": 49218,
          "net": 19254
        },
        {
          "gross": 40000,
          "cost": 64188,
          "net": 25646
        },
        {
          "gross": 50000,
          "cost": 79159,
          "net": 31898
        },
        {
          "gross": 60000,
          "cost": 94130,
          "net": 38150
        },
        {
          "gross": 70000,
          "cost": 108432,
          "net": 44402
        },
        {
          "gross": 80000,
          "cost": 121683,
          "net": 50272
        },
        {
          "gross": 90000,
          "cost": 132878,
          "net": 55322
        },
        {
          "gross": 100000,
          "cost": 144073,
          "net": 60372
        },
        {
          "gross": 110000,
          "cost": 155268,
          "net": 65422
        },
        {
          "gross": 120000,
          "cost": 166463,
          "net": 70472
        },
        {
          "gross": 130000,
          "cost": 177658,
          "net": 75522
        },
        {
          "gross": 140000,
          "cost": 188853,
          "net": 80572
        },
        {
          "gross": 150000,
          "cost": 200048,
          "net": 85622
        }
      ]
    },
    {
      "name": "Norway",
      "flag": "🇳🇴",
      "eu": false,
      "devSalary": 70700,
      "costOfLiving": 26474,
      "points": [
        {
          "gross": 20000,
          "cost": 30858,
          "net": 14076
        },
        {
          "gross": 30000,
          "cost": 43864,
          "net": 20877
        },
        {
          "gross": 40000,
          "cost": 56871,
          "net": 27497
        },
        {
          "gross": 50000,
          "cost": 69877,
          "net": 34117
        },
        {
          "gross": 60000,
          "cost": 82884,
          "net": 40737
        },
        {
          "gross": 70000,
          "cost": 95890,
          "net": 46755
        },
        {
          "gross": 80000,
          "cost": 108897,
          "net": 52455
        },
        {
          "gross": 90000,
          "cost": 121904,
          "net": 58037
        },
        {
          "gross": 100000,
          "cost": 134910,
          "net": 63457
        },
        {
          "gross": 110000,
          "cost": 147917,
          "net": 68877
        },
        {
          "gross": 120000,
          "cost": 160923,
          "net": 74297
        },
        {
          "gross": 130000,
          "cost": 173930,
          "net": 79692
        },
        {
          "gross": 140000,
          "cost": 186937,
          "net": 84952
        },
        {
          "gross": 150000,
          "cost": 199943,
          "net": 90212
        }
      ]
    },
    {
      "name": "Poland",
      "flag": "🇵🇱",
      "eu": true,
      "devSalary": 30000,
      "costOfLiving": 16551,
      "points": [
        {
          "gross": 20000,
          "cost": 28399,
          "net": 13881
        },
        {
          "gross": 30000,
          "cost": 40647,
          "net": 19894
        },
        {
          "gross": 40000,
          "cost": 52895,
          "net": 24868
        },
        {
          "gross": 50000,
          "cost": 65143,
          "net": 30523
        },
        {
          "gross": 60000,
          "cost": 77391,
          "net": 36178
        },
        {
          "gross": 70000,
          "cost": 89639,
          "net": 41833
        },
        {
          "gross": 80000,
          "cost": 101887,
          "net": 47488
        },
        {
          "gross": 90000,
          "cost": 114135,
          "net": 53143
        },
        {
          "gross": 100000,
          "cost": 126383,
          "net": 58798
        },
        {
          "gross": 110000,
          "cost": 138631,
          "net": 64453
        },
        {
          "gross": 120000,
          "cost": 150879,
          "net": 70108
        },
        {
          "gross": 130000,
          "cost": 163127,
          "net": 75763
        },
        {
          "gross": 140000,
          "cost": 175375,
          "net": 81418
        },
        {
          "gross": 150000,
          "cost": 187623,
          "net": 87073
        }
      ]
    },
    {
      "name": "Portugal",
      "flag": "🇵🇹",
      "eu": true,
      "devSalary": 31200,
      "costOfLiving": 19314,
      "points": [
        {
          "gross": 20000,
          "cost": 28576,
          "net": 13295
        },
        {
          "gross": 30000,
          "cost": 41251,
          "net": 18617
        },
        {
          "gross": 40000,
          "cost": 53926,
          "net": 23575
        },
        {
          "gross": 50000,
          "cost": 66601,
          "net": 27975
        },
        {
          "gross": 60000,
          "cost": 79276,
          "net": 32375
        },
        {
          "gross": 70000,
          "cost": 91951,
          "net": 36775
        },
        {
          "gross": 80000,
          "cost": 104626,
          "net": 41175
        },
        {
          "gross": 90000,
          "cost": 117301,
          "net": 45067
        },
        {
          "gross": 100000,
          "cost": 129976,
          "net": 48917
        },
        {
          "gross": 110000,
          "cost": 142651,
          "net": 52767
        },
        {
          "gross": 120000,
          "cost": 155326,
          "net": 56617
        },
        {
          "gross": 130000,
          "cost": 168001,
          "net": 60467
        },
        {
          "gross": 140000,
          "cost": 180676,
          "net": 64317
        },
        {
          "gross": 150000,
          "cost": 193351,
          "net": 68167
        }
      ]
    },
    {
      "name": "Romania",
      "flag": "🇷🇴",
      "eu": true,
      "devSalary": 24700,
      "costOfLiving": 12567,
      "points": [
        {
          "gross": 20000,
          "cost": 24076,
          "net": 11000
        },
        {
          "gross": 30000,
          "cost": 34501,
          "net": 16500
        },
        {
          "gross": 40000,
          "cost": 44926,
          "net": 22000
        },
        {
          "gross": 50000,
          "cost": 55351,
          "net": 27500
        },
        {
          "gross": 60000,
          "cost": 65776,
          "net": 33000
        },
        {
          "gross": 70000,
          "cost": 76201,
          "net": 38500
        },
        {
          "gross": 80000,
          "cost": 86626,
          "net": 44000
        },
        {
          "gross": 90000,
          "cost": 97051,
          "net": 49500
        },
        {
          "gross": 100000,
          "cost": 107476,
          "net": 55000
        },
        {
          "gross": 110000,
          "cost": 117901,
          "net": 60500
        },
        {
          "gross": 120000,
          "cost": 128326,
          "net": 66000
        },
        {
          "gross": 130000,
          "cost": 138751,
          "net": 71500
        },
        {
          "gross": 140000,
          "cost": 149176,
          "net": 77000
        },
        {
          "gross": 150000,
          "cost": 159601,
          "net": 82500
        }
      ]
    },
    {
      "name": "Serbia",
      "flag": "🇷🇸",
      "eu": false,
      "devSalary": 25300,
      "costOfLiving": 13495,
      "points": [
        {
          "gross": 20000,
          "cost": 26911,
          "net": 14036
        },
        {
          "gross": 30000,
          "cost": 38626,
          "net": 21046
        },
        {
          "gross": 40000,
          "cost": 50341,
          "net": 28056
        },
        {
          "gross": 50000,
          "cost": 62056,
          "net": 35066
        },
        {
          "gross": 60000,
          "cost": 73771,
          "net": 42076
        },
        {
          "gross": 70000,
          "cost": 84850,
          "net": 49890
        },
        {
          "gross": 80000,
          "cost": 95050,
          "net": 58814
        },
        {
          "gross": 90000,
          "cost": 105250,
          "net": 67740
        },
        {
          "gross": 100000,
          "cost": 115450,
          "net": 76664
        },
        {
          "gross": 110000,
          "cost": 125650,
          "net": 85590
        },
        {
          "gross": 120000,
          "cost": 135850,
          "net": 94514
        },
        {
          "gross": 130000,
          "cost": 146050,
          "net": 103440
        },
        {
          "gross": 140000,
          "cost": 156250,
          "net": 112364
        },
        {
          "gross": 150000,
          "cost": 166450,
          "net": 121290
        }
      ]
    },
    {
      "name": "Slovakia",
      "flag": "🇸🇰",
      "eu": true,
      "devSalary": 29000,
      "costOfLiving": 16192,
      "points": [
        {
          "gross": 20000,
          "cost": 32484,
          "net": 13320
        },
        {
          "gross": 30000,
          "cost": 46304,
          "net": 19980
        },
        {
          "gross": 40000,
          "cost": 60124,
          "net": 26640
        },
        {
          "gross": 50000,
          "cost": 73944,
          "net": 32939
        },
        {
          "gross": 60000,
          "cost": 87764,
          "net": 38999
        },
        {
          "gross": 70000,
          "cost": 101584,
          "net": 44576
        },
        {
          "gross": 80000,
          "cost": 115404,
          "net": 49887
        },
        {
          "gross": 90000,
          "cost": 129224,
          "net": 54947
        },
        {
          "gross": 100000,
          "cost": 143044,
          "net": 60007
        },
        {
          "gross": 110000,
          "cost": 156864,
          "net": 65067
        },
        {
          "gross": 120000,
          "cost": 170684,
          "net": 70127
        },
        {
          "gross": 130000,
          "cost": 184504,
          "net": 75187
        },
        {
          "gross": 140000,
          "cost": 198324,
          "net": 80247
        },
        {
          "gross": 150000,
          "cost": 212144,
          "net": 85307
        }
      ]
    },
    {
      "name": "Spain",
      "flag": "🇪🇸",
      "eu": true,
      "devSalary": 36800,
      "costOfLiving": 19676,
      "points": [
        {
          "gross": 20000,
          "cost": 30146,
          "net": 14522
        },
        {
          "gross": 30000,
          "cost": 43606,
          "net": 20884
        },
        {
          "gross": 40000,
          "cost": 57066,
          "net": 26898
        },
        {
          "gross": 50000,
          "cost": 70526,
          "net": 32548
        },
        {
          "gross": 60000,
          "cost": 83986,
          "net": 38198
        },
        {
          "gross": 70000,
          "cost": 94668,
          "net": 43602
        },
        {
          "gross": 80000,
          "cost": 104973,
          "net": 49081
        },
        {
          "gross": 90000,
          "cost": 115277,
          "net": 54560
        },
        {
          "gross": 100000,
          "cost": 125595,
          "net": 60036
        },
        {
          "gross": 110000,
          "cost": 135917,
          "net": 65511
        },
        {
          "gross": 120000,
          "cost": 146239,
          "net": 70986
        },
        {
          "gross": 130000,
          "cost": 156561,
          "net": 76462
        },
        {
          "gross": 140000,
          "cost": 166882,
          "net": 81937
        },
        {
          "gross": 150000,
          "cost": 177204,
          "net": 87412
        }
      ]
    },
    {
      "name": "Sweden",
      "flag": "🇸🇪",
      "eu": true,
      "devSalary": 61400,
      "costOfLiving": 21098,
      "points": [
        {
          "gross": 20000,
          "cost": 31765,
          "net": 12118
        },
        {
          "gross": 30000,
          "cost": 45225,
          "net": 18177
        },
        {
          "gross": 40000,
          "cost": 58686,
          "net": 24236
        },
        {
          "gross": 50000,
          "cost": 72146,
          "net": 30295
        },
        {
          "gross": 60000,
          "cost": 85606,
          "net": 35424
        },
        {
          "gross": 70000,
          "cost": 99066,
          "net": 39483
        },
        {
          "gross": 80000,
          "cost": 112527,
          "net": 43542
        },
        {
          "gross": 90000,
          "cost": 125987,
          "net": 47601
        },
        {
          "gross": 100000,
          "cost": 139447,
          "net": 51660
        },
        {
          "gross": 110000,
          "cost": 152907,
          "net": 55719
        },
        {
          "gross": 120000,
          "cost": 166368,
          "net": 59778
        },
        {
          "gross": 130000,
          "cost": 179828,
          "net": 63837
        },
        {
          "gross": 140000,
          "cost": 193288,
          "net": 67896
        },
        {
          "gross": 150000,
          "cost": 206749,
          "net": 71955
        }
      ]
    },
    {
      "name": "Switzerland",
      "flag": "🇨🇭",
      "eu": false,
      "devSalary": 59100,
      "costOfLiving": 40071,
      "points": [
        {
          "gross": 20000,
          "cost": 30376,
          "net": 16708
        },
        {
          "gross": 30000,
          "cost": 42333,
          "net": 25003
        },
        {
          "gross": 40000,
          "cost": 54290,
          "net": 33291
        },
        {
          "gross": 50000,
          "cost": 66247,
          "net": 41468
        },
        {
          "gross": 60000,
          "cost": 78204,
          "net": 49571
        },
        {
          "gross": 70000,
          "cost": 90160,
          "net": 57646
        },
        {
          "gross": 80000,
          "cost": 102117,
          "net": 65627
        },
        {
          "gross": 90000,
          "cost": 114074,
          "net": 73358
        },
        {
          "gross": 100000,
          "cost": 126031,
          "net": 81070
        },
        {
          "gross": 110000,
          "cost": 137988,
          "net": 88778
        },
        {
          "gross": 120000,
          "cost": 149944,
          "net": 96270
        },
        {
          "gross": 130000,
          "cost": 161901,
          "net": 103762
        },
        {
          "gross": 140000,
          "cost": 173858,
          "net": 111254
        },
        {
          "gross": 150000,
          "cost": 185815,
          "net": 118585
        }
      ]
    },
    {
      "name": "Turkey",
      "flag": "🇹🇷",
      "eu": false,
      "devSalary": 26800,
      "costOfLiving": 12302,
      "points": [
        {
          "gross": 20000,
          "cost": 27437,
          "net": 14141
        },
        {
          "gross": 30000,
          "cost": 39812,
          "net": 20709
        },
        {
          "gross": 40000,
          "cost": 52187,
          "net": 27109
        },
        {
          "gross": 50000,
          "cost": 64562,
          "net": 33509
        },
        {
          "gross": 60000,
          "cost": 76937,
          "net": 39909
        },
        {
          "gross": 70000,
          "cost": 89312,
          "net": 46309
        },
        {
          "gross": 80000,
          "cost": 101687,
          "net": 52670
        },
        {
          "gross": 90000,
          "cost": 114062,
          "net": 58570
        },
        {
          "gross": 100000,
          "cost": 126437,
          "net": 64470
        },
        {
          "gross": 110000,
          "cost": 138812,
          "net": 70370
        },
        {
          "gross": 120000,
          "cost": 151187,
          "net": 76270
        },
        {
          "gross": 130000,
          "cost": 163562,
          "net": 82170
        },
        {
          "gross": 140000,
          "cost": 175937,
          "net": 88070
        },
        {
          "gross": 150000,
          "cost": 188312,
          "net": 93970
        }
      ]
    },
    {
      "name": "Ukraine",
      "flag": "🇺🇦",
      "eu": false,
      "devSalary": 24100,
      "costOfLiving": 8953,
      "points": [
        {
          "gross": 20000,
          "cost": 28026,
          "net": 15400
        },
        {
          "gross": 30000,
          "cost": 40426,
          "net": 23100
        },
        {
          "gross": 40000,
          "cost": 52826,
          "net": 30800
        },
        {
          "gross": 50000,
          "cost": 65226,
          "net": 38500
        },
        {
          "gross": 60000,
          "cost": 77626,
          "net": 46200
        },
        {
          "gross": 70000,
          "cost": 90026,
          "net": 53900
        },
        {
          "gross": 80000,
          "cost": 102426,
          "net": 61600
        },
        {
          "gross": 90000,
          "cost": 114826,
          "net": 69300
        },
        {
          "gross": 100000,
          "cost": 127226,
          "net": 77000
        },
        {
          "gross": 110000,
          "cost": 139626,
          "net": 84700
        },
        {
          "gross": 120000,
          "cost": 152026,
          "net": 92400
        },
        {
          "gross": 130000,
          "cost": 164426,
          "net": 100100
        },
        {
          "gross": 140000,
          "cost": 176826,
          "net": 107800
        },
        {
          "gross": 150000,
          "cost": 189226,
          "net": 115500
        }
      ]
    },
    {
      "name": "United Kingdom",
      "flag": "🇬🇧",
      "eu": false,
      "devSalary": 62100,
      "costOfLiving": 26162,
      "points": [
        {
          "gross": 20000,
          "cost": 28405,
          "net": 17382
        },
        {
          "gross": 30000,
          "cost": 40455,
          "net": 24082
        },
        {
          "gross": 40000,
          "cost": 52505,
          "net": 30782
        },
        {
          "gross": 50000,
          "cost": 64555,
          "net": 37482
        },
        {
          "gross": 60000,
          "cost": 76605,
          "net": 43742
        },
        {
          "gross": 70000,
          "cost": 88655,
          "net": 49042
        },
        {
          "gross": 80000,
          "cost": 100705,
          "net": 54342
        },
        {
          "gross": 90000,
          "cost": 112755,
          "net": 59642
        },
        {
          "gross": 100000,
          "cost": 124805,
          "net": 64942
        },
        {
          "gross": 110000,
          "cost": 136855,
          "net": 70242
        },
        {
          "gross": 120000,
          "cost": 148905,
          "net": 75542
        },
        {
          "gross": 130000,
          "cost": 160955,
          "net": 80842
        },
        {
          "gross": 140000,
          "cost": 173005,
          "net": 86142
        },
        {
          "gross": 150000,
          "cost": 185055,
          "net": 91019
        }
      ]
    },
    {
      "name": "Seattle, WA",
      "flag": "🇺🇸",
      "eu": false,
      "us": true,
      "approx": true,
      "devSalary": 118325,
      "costOfLiving": 40522,
      "points": [
        {
          "gross": 0,
          "cost": 0,
          "net": 0
        },
        {
          "gross": 118325,
          "cost": 136582,
          "net": 89612
        }
      ],
      "note": "blog-based (API US income tax unreliable)"
    },
    {
      "name": "San Francisco, CA",
      "flag": "🇺🇸",
      "eu": false,
      "us": true,
      "approx": true,
      "devSalary": 105489,
      "costOfLiving": 50802,
      "points": [
        {
          "gross": 0,
          "cost": 0,
          "net": 0
        },
        {
          "gross": 105489,
          "cost": 126994,
          "net": 73427
        }
      ],
      "note": "blog-based (API US income tax unreliable)"
    },
    {
      "name": "New York, NY",
      "flag": "🇺🇸",
      "eu": false,
      "us": true,
      "approx": true,
      "devSalary": 97467,
      "costOfLiving": 60046,
      "points": [
        {
          "gross": 0,
          "cost": 0,
          "net": 0
        },
        {
          "gross": 97467,
          "cost": 113832,
          "net": 70572
        }
      ],
      "note": "blog-based (API US income tax unreliable)"
    },
    {
      "name": "Austin, TX",
      "flag": "🇺🇸",
      "eu": false,
      "us": true,
      "approx": true,
      "devSalary": 100575,
      "costOfLiving": 35197,
      "points": [
        {
          "gross": 0,
          "cost": 0,
          "net": 0
        },
        {
          "gross": 100575,
          "cost": 111035,
          "net": 78176
        }
      ],
      "note": "blog-based (API US income tax unreliable)"
    },
    {
      "name": "Atlanta, GA",
      "flag": "🇺🇸",
      "eu": false,
      "us": true,
      "approx": true,
      "devSalary": 100977,
      "costOfLiving": 33187,
      "points": [
        {
          "gross": 0,
          "cost": 0,
          "net": 0
        },
        {
          "gross": 100977,
          "cost": 110964,
          "net": 73588
        }
      ],
      "note": "blog-based (API US income tax unreliable)"
    }
  ]
}